[{"type":"Feature","id":"data.954","geometry":{"type":"Point","coordinates":[101.92959566,21.26084902]},"geometry_name":"the_geom","properties":{"uuid":207010,"usid":207,"urid":2,"urcne":"Phongsaly","uscne":"Boontai District","uucne":"B. Long nay kow"},"bbox":[101.92959566,21.26084902,101.92959566,21.26084902]},{"type":"Feature","id":"data.960","geometry":{"type":"Point","coordinates":[101.95431582,21.23994799]},"geometry_name":"the_geom","properties":{"uuid":207016,"usid":207,"urid":2,"urcne":"Phongsaly","uscne":"Boontai District","uucne":"B. Bor noi"},"bbox":[101.95431582,21.23994799,101.95431582,21.23994799]},{"type":"Feature","id":"data.961","geometry":{"type":"Point","coordinates":[101.94250882,21.29070134]},"geometry_name":"the_geom","properties":{"uuid":207017,"usid":207,"urid":2,"urcne":"Phongsaly","uscne":"Boontai District","uucne":"B. Char luang may"},"bbox":[101.94250882,21.29070134,101.94250882,21.29070134]}]