[{"type":"Feature","id":"data.393","geometry":{"type":"Point","coordinates":[102.20519708,18.37689213]},"geometry_name":"the_geom","properties":{"uuid":108001,"usid":108,"urid":1,"urcne":"Vientiane Capital","uscne":"Sangthong District","uucne":"B. Koua"},"bbox":[102.20519708,18.37689213,102.20519708,18.37689213]},{"type":"Feature","id":"data.394","geometry":{"type":"Point","coordinates":[102.2190392,18.34762939]},"geometry_name":"the_geom","properties":{"uuid":108002,"usid":108,"urid":1,"urcne":"Vientiane Capital","uscne":"Sangthong District","uucne":"B. Taohay"},"bbox":[102.2190392,18.34762939,102.2190392,18.34762939]},{"type":"Feature","id":"data.397","geometry":{"type":"Point","coordinates":[102.21704104,18.32981626]},"geometry_name":"the_geom","properties":{"uuid":108005,"usid":108,"urid":1,"urcne":"Vientiane Capital","uscne":"Sangthong District","uucne":"B. Nalath"},"bbox":[102.21704104,18.32981626,102.21704104,18.32981626]},{"type":"Feature","id":"data.398","geometry":{"type":"Point","coordinates":[102.20150669,18.31363491]},"geometry_name":"the_geom","properties":{"uuid":108007,"usid":108,"urid":1,"urcne":"Vientiane Capital","uscne":"Sangthong District","uucne":"B. Nongboua"},"bbox":[102.20150669,18.31363491,102.20150669,18.31363491]},{"type":"Feature","id":"data.399","geometry":{"type":"Point","coordinates":[102.22341782,18.30838289]},"geometry_name":"the_geom","properties":{"uuid":108009,"usid":108,"urid":1,"urcne":"Vientiane Capital","uscne":"Sangthong District","uucne":"B. Natan"},"bbox":[102.22341782,18.30838289,102.22341782,18.30838289]}]