[{"type":"Feature","id":"data.2378","geometry":{"type":"Point","coordinates":[102.319572,20.60556876]},"geometry_name":"the_geom","properties":{"uuid":605051,"usid":605,"urid":6,"urcne":"Louangphabang","uscne":"Nambak District","uucne":"B. Donelao"},"bbox":[102.319572,20.60556876,102.319572,20.60556876]},{"type":"Feature","id":"data.2386","geometry":{"type":"Point","coordinates":[102.37673021,20.57500231]},"geometry_name":"the_geom","properties":{"uuid":605062,"usid":605,"urid":6,"urcne":"Louangphabang","uscne":"Nambak District","uucne":"B. Vanghin"},"bbox":[102.37673021,20.57500231,102.37673021,20.57500231]},{"type":"Feature","id":"data.2387","geometry":{"type":"Point","coordinates":[102.35485436,20.57080809]},"geometry_name":"the_geom","properties":{"uuid":605064,"usid":605,"urid":6,"urcne":"Louangphabang","uscne":"Nambak District","uucne":"B. Nammong"},"bbox":[102.35485436,20.57080809,102.35485436,20.57080809]},{"type":"Feature","id":"data.2388","geometry":{"type":"Point","coordinates":[102.31581381,20.57591963]},"geometry_name":"the_geom","properties":{"uuid":605065,"usid":605,"urid":6,"urcne":"Louangphabang","uscne":"Nambak District","uucne":"B. Namjerth"},"bbox":[102.31581381,20.57591963,102.31581381,20.57591963]},{"type":"Feature","id":"data.2404","geometry":{"type":"Point","coordinates":[102.39854746,20.55906781]},"geometry_name":"the_geom","properties":{"uuid":605089,"usid":605,"urid":6,"urcne":"Louangphabang","uscne":"Nambak District","uucne":"B. Nakork"},"bbox":[102.39854746,20.55906781,102.39854746,20.55906781]},{"type":"Feature","id":"data.2408","geometry":{"type":"Point","coordinates":[102.37259433,20.53575187]},"geometry_name":"the_geom","properties":{"uuid":605098,"usid":605,"urid":6,"urcne":"Louangphabang","uscne":"Nambak District","uucne":"B. Tharbou"},"bbox":[102.37259433,20.53575187,102.37259433,20.53575187]},{"type":"Feature","id":"data.2409","geometry":{"type":"Point","coordinates":[102.38214266,20.54290532]},"geometry_name":"the_geom","properties":{"uuid":605099,"usid":605,"urid":6,"urcne":"Louangphabang","uscne":"Nambak District","uucne":"B. Phonxieng"},"bbox":[102.38214266,20.54290532,102.38214266,20.54290532]},{"type":"Feature","id":"data.2413","geometry":{"type":"Point","coordinates":[102.37063154,20.53000012]},"geometry_name":"the_geom","properties":{"uuid":605109,"usid":605,"urid":6,"urcne":"Louangphabang","uscne":"Nambak District","uucne":"B. Namkham 2"},"bbox":[102.37063154,20.53000012,102.37063154,20.53000012]}]