[{"type":"Feature","id":"data.2385","geometry":{"type":"Point","coordinates":[102.40789337,20.57670853]},"geometry_name":"the_geom","properties":{"uuid":605060,"usid":605,"urid":6,"urcne":"Louangphabang","uscne":"Nambak District","uucne":"B. Parkmong"},"bbox":[102.40789337,20.57670853,102.40789337,20.57670853]},{"type":"Feature","id":"data.2392","geometry":{"type":"Point","coordinates":[102.42208963,20.58354942]},"geometry_name":"the_geom","properties":{"uuid":605073,"usid":605,"urid":6,"urcne":"Louangphabang","uscne":"Nambak District","uucne":"B. Vangkham"},"bbox":[102.42208963,20.58354942,102.42208963,20.58354942]}]