[{"type":"Feature","id":"data.296","geometry":{"type":"Point","coordinates":[102.81404159,18.11270325]},"geometry_name":"the_geom","properties":{"uuid":106068,"usid":106,"urid":1,"urcne":"Vientiane Capital","uscne":"Xaythany District","uucne":"B. San ou dom"},"bbox":[102.81404159,18.11270325,102.81404159,18.11270325]},{"type":"Feature","id":"data.316","geometry":{"type":"Point","coordinates":[102.75993356,18.06210875]},"geometry_name":"the_geom","properties":{"uuid":106088,"usid":106,"urid":1,"urcne":"Vientiane Capital","uscne":"Xaythany District","uucne":"B. Naun thong"},"bbox":[102.75993356,18.06210875,102.75993356,18.06210875]},{"type":"Feature","id":"data.320","geometry":{"type":"Point","coordinates":[102.77647281,18.06593257]},"geometry_name":"the_geom","properties":{"uuid":106092,"usid":106,"urid":1,"urcne":"Vientiane Capital","uscne":"Xaythany District","uucne":"B. Phi lom"},"bbox":[102.77647281,18.06593257,102.77647281,18.06593257]},{"type":"Feature","id":"data.321","geometry":{"type":"Point","coordinates":[102.78497818,18.0531754]},"geometry_name":"the_geom","properties":{"uuid":106093,"usid":106,"urid":1,"urcne":"Vientiane Capital","uscne":"Xaythany District","uucne":"B. Sang khom"},"bbox":[102.78497818,18.0531754,102.78497818,18.0531754]},{"type":"Feature","id":"data.322","geometry":{"type":"Point","coordinates":[102.78966668,18.06226431]},"geometry_name":"the_geom","properties":{"uuid":106094,"usid":106,"urid":1,"urcne":"Vientiane Capital","uscne":"Xaythany District","uucne":"B. Saum sa vanh"},"bbox":[102.78966668,18.06226431,102.78966668,18.06226431]},{"type":"Feature","id":"data.323","geometry":{"type":"Point","coordinates":[102.80647189,18.05988058]},"geometry_name":"the_geom","properties":{"uuid":106095,"usid":106,"urid":1,"urcne":"Vientiane Capital","uscne":"Xaythany District","uucne":"B. Khauk sar vang"},"bbox":[102.80647189,18.05988058,102.80647189,18.05988058]},{"type":"Feature","id":"data.324","geometry":{"type":"Point","coordinates":[102.82055466,18.05729116]},"geometry_name":"the_geom","properties":{"uuid":106096,"usid":106,"urid":1,"urcne":"Vientiane Capital","uscne":"Xaythany District","uucne":"B. Phaun sa vanh"},"bbox":[102.82055466,18.05729116,102.82055466,18.05729116]},{"type":"Feature","id":"data.325","geometry":{"type":"Point","coordinates":[102.81734079,18.04413769]},"geometry_name":"the_geom","properties":{"uuid":106097,"usid":106,"urid":1,"urcne":"Vientiane Capital","uscne":"Xaythany District","uucne":"B. Don loum"},"bbox":[102.81734079,18.04413769,102.81734079,18.04413769]},{"type":"Feature","id":"data.326","geometry":{"type":"Point","coordinates":[102.8357006,18.05477961]},"geometry_name":"the_geom","properties":{"uuid":106098,"usid":106,"urid":1,"urcne":"Vientiane Capital","uscne":"Xaythany District","uucne":"B. Na pha sook"},"bbox":[102.8357006,18.05477961,102.8357006,18.05477961]}]