[{"type":"Feature","id":"data.602","geometry":{"type":"Point","coordinates":[102.76454721,21.43491441]},"geometry_name":"the_geom","properties":{"uuid":202083,"usid":202,"urid":2,"urcne":"Phongsaly","uscne":"May District","uucne":"B. San tar"},"bbox":[102.76454721,21.43491441,102.76454721,21.43491441]},{"type":"Feature","id":"data.607","geometry":{"type":"Point","coordinates":[102.76624127,21.43137247]},"geometry_name":"the_geom","properties":{"uuid":202091,"usid":202,"urid":2,"urcne":"Phongsaly","uscne":"May District","uucne":"B. Phon say"},"bbox":[102.76624127,21.43137247,102.76624127,21.43137247]},{"type":"Feature","id":"data.608","geometry":{"type":"Point","coordinates":[102.81890988,21.47078544]},"geometry_name":"the_geom","properties":{"uuid":202092,"usid":202,"urid":2,"urcne":"Phongsaly","uscne":"May District","uucne":"B. Houai arn tang luang"},"bbox":[102.81890988,21.47078544,102.81890988,21.47078544]}]