[{"type":"Feature","id":"data.463","geometry":{"type":"Point","coordinates":[103.02021964,18.02041741]},"geometry_name":"the_geom","properties":{"uuid":109036,"usid":109,"urid":1,"urcne":"Vientiane Capital","uscne":"Mayparkngum District","uucne":"B. Nongvangpherng"},"bbox":[103.02021964,18.02041741,103.02021964,18.02041741]},{"type":"Feature","id":"data.466","geometry":{"type":"Point","coordinates":[103.02098114,17.99911774]},"geometry_name":"the_geom","properties":{"uuid":109039,"usid":109,"urid":1,"urcne":"Vientiane Capital","uscne":"Mayparkngum District","uucne":"B. Dongkaleum"},"bbox":[103.02098114,17.99911774,103.02098114,17.99911774]},{"type":"Feature","id":"data.469","geometry":{"type":"Point","coordinates":[103.01659439,17.97760483]},"geometry_name":"the_geom","properties":{"uuid":109042,"usid":109,"urid":1,"urcne":"Vientiane Capital","uscne":"Mayparkngum District","uucne":"B. Thinthieng"},"bbox":[103.01659439,17.97760483,103.01659439,17.97760483]},{"type":"Feature","id":"data.470","geometry":{"type":"Point","coordinates":[103.00960556,17.99394183]},"geometry_name":"the_geom","properties":{"uuid":109043,"usid":109,"urid":1,"urcne":"Vientiane Capital","uscne":"Mayparkngum District","uucne":"B. Donevangpho"},"bbox":[103.00960556,17.99394183,103.00960556,17.99394183]},{"type":"Feature","id":"data.471","geometry":{"type":"Point","coordinates":[102.96365311,18.00906815]},"geometry_name":"the_geom","properties":{"uuid":109044,"usid":109,"urid":1,"urcne":"Vientiane Capital","uscne":"Mayparkngum District","uucne":"B. Maknaotai"},"bbox":[102.96365311,18.00906815,102.96365311,18.00906815]},{"type":"Feature","id":"data.472","geometry":{"type":"Point","coordinates":[102.95925572,18.0098951]},"geometry_name":"the_geom","properties":{"uuid":109045,"usid":109,"urid":1,"urcne":"Vientiane Capital","uscne":"Mayparkngum District","uucne":"B. Maknaoneua"},"bbox":[102.95925572,18.0098951,102.95925572,18.0098951]},{"type":"Feature","id":"data.474","geometry":{"type":"Point","coordinates":[102.95909235,18.01807207]},"geometry_name":"the_geom","properties":{"uuid":109047,"usid":109,"urid":1,"urcne":"Vientiane Capital","uscne":"Mayparkngum District","uucne":"B. Maknaodong"},"bbox":[102.95909235,18.01807207,102.95909235,18.01807207]}]