[{"type":"Feature","id":"data.3240","geometry":{"type":"Point","coordinates":[104.63294257,19.97878262]},"geometry_name":"the_geom","properties":{"uuid":706007,"usid":706,"urid":7,"urcne":"Houaphan","uscne":"Xamtay District","uucne":"B. Sobsanh"},"bbox":[104.63294257,19.97878262,104.63294257,19.97878262]},{"type":"Feature","id":"data.3243","geometry":{"type":"Point","coordinates":[104.67647055,19.97052016]},"geometry_name":"the_geom","properties":{"uuid":706011,"usid":706,"urid":7,"urcne":"Houaphan","uscne":"Xamtay District","uucne":"B. Phattay"},"bbox":[104.67647055,19.97052016,104.67647055,19.97052016]},{"type":"Feature","id":"data.3244","geometry":{"type":"Point","coordinates":[104.66466556,19.97117403]},"geometry_name":"the_geom","properties":{"uuid":706012,"usid":706,"urid":7,"urcne":"Houaphan","uscne":"Xamtay District","uucne":"B. Phatkang"},"bbox":[104.66466556,19.97117403,104.66466556,19.97117403]},{"type":"Feature","id":"data.3245","geometry":{"type":"Point","coordinates":[104.65870067,19.97311788]},"geometry_name":"the_geom","properties":{"uuid":706013,"usid":706,"urid":7,"urcne":"Houaphan","uscne":"Xamtay District","uucne":"B. Phatnuea"},"bbox":[104.65870067,19.97311788,104.65870067,19.97311788]},{"type":"Feature","id":"data.3246","geometry":{"type":"Point","coordinates":[104.68124254,19.96713437]},"geometry_name":"the_geom","properties":{"uuid":706014,"usid":706,"urid":7,"urcne":"Houaphan","uscne":"Xamtay District","uucne":"B. Hanglong"},"bbox":[104.68124254,19.96713437,104.68124254,19.96713437]},{"type":"Feature","id":"data.3316","geometry":{"type":"Point","coordinates":[104.64325022,19.90864193]},"geometry_name":"the_geom","properties":{"uuid":706219,"usid":706,"urid":7,"urcne":"Houaphan","uscne":"Xamtay District","uucne":"B. Pomkhor"},"bbox":[104.64325022,19.90864193,104.64325022,19.90864193]}]