[{"type":"Feature","id":"data.5315","geometry":{"type":"Point","coordinates":[105.19596574,17.34748076]},"geometry_name":"the_geom","properties":{"uuid":1202006,"usid":1202,"urid":12,"urcne":"Khammouan","uscne":"Mahaxay District","uucne":"B. Phar nang"},"bbox":[105.19596574,17.34748076,105.19596574,17.34748076]},{"type":"Feature","id":"data.5340","geometry":{"type":"Point","coordinates":[105.2399056,17.33187692]},"geometry_name":"the_geom","properties":{"uuid":1202042,"usid":1202,"urid":12,"urcne":"Khammouan","uscne":"Mahaxay District","uucne":"B. Phar khaen"},"bbox":[105.2399056,17.33187692,105.2399056,17.33187692]}]