[{"type":"Feature","id":"data.7091","geometry":{"type":"Point","coordinates":[105.70482999,15.79552663]},"geometry_name":"the_geom","properties":{"uuid":1404058,"usid":1404,"urid":14,"urcne":"Salavan","uscne":"Lakhonepheng District","uucne":"B. Luck 90"},"bbox":[105.70482999,15.79552663,105.70482999,15.79552663]},{"type":"Feature","id":"data.7094","geometry":{"type":"Point","coordinates":[105.72203485,15.79282128]},"geometry_name":"the_geom","properties":{"uuid":1404061,"usid":1404,"urid":14,"urcne":"Salavan","uscne":"Lakhonepheng District","uucne":"B. Lak 94"},"bbox":[105.72203485,15.79282128,105.72203485,15.79282128]},{"type":"Feature","id":"data.7095","geometry":{"type":"Point","coordinates":[105.73220286,15.7600099]},"geometry_name":"the_geom","properties":{"uuid":1404062,"usid":1404,"urid":14,"urcne":"Salavan","uscne":"Lakhonepheng District","uucne":"B. Lak 90"},"bbox":[105.73220286,15.7600099,105.73220286,15.7600099]},{"type":"Feature","id":"data.7096","geometry":{"type":"Point","coordinates":[105.72346237,15.77306095]},"geometry_name":"the_geom","properties":{"uuid":1404063,"usid":1404,"urid":14,"urcne":"Salavan","uscne":"Lakhonepheng District","uucne":"B. Nasomhong"},"bbox":[105.72346237,15.77306095,105.72346237,15.77306095]},{"type":"Feature","id":"data.7097","geometry":{"type":"Point","coordinates":[105.73664241,15.75375558]},"geometry_name":"the_geom","properties":{"uuid":1404064,"usid":1404,"urid":14,"urcne":"Salavan","uscne":"Lakhonepheng District","uucne":"B. Dongtaloung"},"bbox":[105.73664241,15.75375558,105.73664241,15.75375558]},{"type":"Feature","id":"data.7098","geometry":{"type":"Point","coordinates":[105.76694978,15.76702639]},"geometry_name":"the_geom","properties":{"uuid":1404065,"usid":1404,"urid":14,"urcne":"Salavan","uscne":"Lakhonepheng District","uucne":"B. Nakhandai"},"bbox":[105.76694978,15.76702639,105.76694978,15.76702639]},{"type":"Feature","id":"data.7099","geometry":{"type":"Point","coordinates":[105.75551494,15.77124484]},"geometry_name":"the_geom","properties":{"uuid":1404066,"usid":1404,"urid":14,"urcne":"Salavan","uscne":"Lakhonepheng District","uucne":"B. Poudaochaenggnai"},"bbox":[105.75551494,15.77124484,105.75551494,15.77124484]},{"type":"Feature","id":"data.7100","geometry":{"type":"Point","coordinates":[105.76335621,15.75295963]},"geometry_name":"the_geom","properties":{"uuid":1404071,"usid":1404,"urid":14,"urcne":"Salavan","uscne":"Lakhonepheng District","uucne":"B. DaneKhoum"},"bbox":[105.76335621,15.75295963,105.76335621,15.75295963]},{"type":"Feature","id":"data.7101","geometry":{"type":"Point","coordinates":[105.74665954,15.7386938]},"geometry_name":"the_geom","properties":{"uuid":1404072,"usid":1404,"urid":14,"urcne":"Salavan","uscne":"Lakhonepheng District","uucne":"B. Danesam"},"bbox":[105.74665954,15.7386938,105.74665954,15.7386938]},{"type":"Feature","id":"data.7103","geometry":{"type":"Point","coordinates":[105.77526849,15.73424083]},"geometry_name":"the_geom","properties":{"uuid":1404075,"usid":1404,"urid":14,"urcne":"Salavan","uscne":"Lakhonepheng District","uucne":"B. Dane1"},"bbox":[105.77526849,15.73424083,105.77526849,15.73424083]}]