[{"type":"Feature","id":"data.5626","geometry":{"type":"Point","coordinates":[105.89519584,17.21860112]},"geometry_name":"the_geom","properties":{"uuid":1206067,"usid":1206,"urid":12,"urcne":"Khammouan","uscne":"Bualapha District","uucne":"B. Phakhiad"},"bbox":[105.89519584,17.21860112,105.89519584,17.21860112]},{"type":"Feature","id":"data.5627","geometry":{"type":"Point","coordinates":[105.95411953,17.189488]},"geometry_name":"the_geom","properties":{"uuid":1206070,"usid":1206,"urid":12,"urcne":"Khammouan","uscne":"Bualapha District","uucne":"B. Houaytha"},"bbox":[105.95411953,17.189488,105.95411953,17.189488]},{"type":"Feature","id":"data.5628","geometry":{"type":"Point","coordinates":[105.95614728,17.1496867]},"geometry_name":"the_geom","properties":{"uuid":1206072,"usid":1206,"urid":12,"urcne":"Khammouan","uscne":"Bualapha District","uucne":"B. Khor"},"bbox":[105.95614728,17.1496867,105.95614728,17.1496867]}]