[{"type":"Feature","id":"data.6214","geometry":{"type":"Point","coordinates":[106.2752294,16.56822712]},"geometry_name":"the_geom","properties":{"uuid":1306065,"usid":1306,"urid":13,"urcne":"Savannakhet","uscne":"Nong District","uucne":"B. Ar luoi"},"bbox":[106.2752294,16.56822712,106.2752294,16.56822712]},{"type":"Feature","id":"data.6215","geometry":{"type":"Point","coordinates":[106.31761903,16.54377778]},"geometry_name":"the_geom","properties":{"uuid":1306068,"usid":1306,"urid":13,"urcne":"Savannakhet","uscne":"Nong District","uucne":"B. Ar lao nhai"},"bbox":[106.31761903,16.54377778,106.31761903,16.54377778]}]