[{"type":"Feature","id":"data.6851","geometry":{"type":"Point","coordinates":[106.43772307,15.53060115]},"geometry_name":"the_geom","properties":{"uuid":1401031,"usid":1401,"urid":14,"urcne":"Salavan","uscne":"Saravane District","uucne":"B. Haphougnai"},"bbox":[106.43772307,15.53060115,106.43772307,15.53060115]},{"type":"Feature","id":"data.7560","geometry":{"type":"Point","coordinates":[106.42740545,15.47260425]},"geometry_name":"the_geom","properties":{"uuid":1504002,"usid":1504,"urid":15,"urcne":"Xekong","uscne":"Thateng District","uucne":"B. San nuea"},"bbox":[106.42740545,15.47260425,106.42740545,15.47260425]},{"type":"Feature","id":"data.7563","geometry":{"type":"Point","coordinates":[106.43899645,15.4633176]},"geometry_name":"the_geom","properties":{"uuid":1504006,"usid":1504,"urid":15,"urcne":"Xekong","uscne":"Thateng District","uucne":"B. Nong nouk"},"bbox":[106.43899645,15.4633176,106.43899645,15.4633176]},{"type":"Feature","id":"data.7565","geometry":{"type":"Point","coordinates":[106.42520679,15.47677182]},"geometry_name":"the_geom","properties":{"uuid":1504009,"usid":1504,"urid":15,"urcne":"Xekong","uscne":"Thateng District","uucne":"B. San tay"},"bbox":[106.42520679,15.47677182,106.42520679,15.47677182]},{"type":"Feature","id":"data.7566","geometry":{"type":"Point","coordinates":[106.45101819,15.48457319]},"geometry_name":"the_geom","properties":{"uuid":1504010,"usid":1504,"urid":15,"urcne":"Xekong","uscne":"Thateng District","uucne":"B. Kow lar kang"},"bbox":[106.45101819,15.48457319,106.45101819,15.48457319]},{"type":"Feature","id":"data.7567","geometry":{"type":"Point","coordinates":[106.46389011,15.50431022]},"geometry_name":"the_geom","properties":{"uuid":1504011,"usid":1504,"urid":15,"urcne":"Xekong","uscne":"Thateng District","uucne":"B. Kow houa phou"},"bbox":[106.46389011,15.50431022,106.46389011,15.50431022]},{"type":"Feature","id":"data.7568","geometry":{"type":"Point","coordinates":[106.47736754,15.46166218]},"geometry_name":"the_geom","properties":{"uuid":1504012,"usid":1504,"urid":15,"urcne":"Xekong","uscne":"Thateng District","uucne":"B. Leek"},"bbox":[106.47736754,15.46166218,106.47736754,15.46166218]},{"type":"Feature","id":"data.7569","geometry":{"type":"Point","coordinates":[106.48648295,15.45887712]},"geometry_name":"the_geom","properties":{"uuid":1504013,"usid":1504,"urid":15,"urcne":"Xekong","uscne":"Thateng District","uucne":"B. Cha lam nhay"},"bbox":[106.48648295,15.45887712,106.48648295,15.45887712]}]