[{"type":"Feature","id":"data.7436","geometry":{"type":"Point","coordinates":[106.92148947,15.55037482]},"geometry_name":"the_geom","properties":{"uuid":1501030,"usid":1501,"urid":15,"urcne":"Xekong","uscne":"Lamarm District","uucne":"B. Chanamtai"},"bbox":[106.92148947,15.55037482,106.92148947,15.55037482]},{"type":"Feature","id":"data.7450","geometry":{"type":"Point","coordinates":[106.92546,15.54841]},"geometry_name":"the_geom","properties":{"uuid":1501046,"usid":1501,"urid":15,"urcne":"Xekong","uscne":"Lamarm District","uucne":"B. Ponephai"},"bbox":[106.92546,15.54841,106.92546,15.54841]},{"type":"Feature","id":"data.7470","geometry":{"type":"Point","coordinates":[106.87097962,15.61769902]},"geometry_name":"the_geom","properties":{"uuid":1502026,"usid":1502,"urid":15,"urcne":"Xekong","uscne":"Kaleum District","uucne":"B. Tangpang"},"bbox":[106.87097962,15.61769902,106.87097962,15.61769902]},{"type":"Feature","id":"data.7496","geometry":{"type":"Point","coordinates":[106.8660322,15.61403822]},"geometry_name":"the_geom","properties":{"uuid":1502072,"usid":1502,"urid":15,"urcne":"Xekong","uscne":"Kaleum District","uucne":"B. Tangkard"},"bbox":[106.8660322,15.61403822,106.8660322,15.61403822]}]